<?xml version="1.0" encoding="UTF-8"?><record_update table="sys_security_acl">
    <sys_security_acl action="DELETE">
        <active>true</active>
        <admin_overrides>true</admin_overrides>
        <advanced>false</advanced>
        <applies_to/>
        <condition/>
        <controlled_by_refs/>
        <decision_type>allow</decision_type>
        <description/>
        <local_or_existing>Existing</local_or_existing>
        <name>x_1831875_amp2_0_complex</name>
        <operation display_value="write">write</operation>
        <script/>
        <security_attribute/>
        <sys_class_name>sys_security_acl</sys_class_name>
        <sys_created_by>admin</sys_created_by>
        <sys_created_on>2025-12-12 02:00:17</sys_created_on>
        <sys_id>4b7a1d8583317e10d18398c6feaad3c0</sys_id>
        <sys_mod_count>0</sys_mod_count>
        <sys_name>x_1831875_amp2_0_complex</sys_name>
        <sys_package display_value="AMP2.0" source="x_1831875_amp2_0">a39c21588331f210d18398c6feaad3b6</sys_package>
        <sys_policy/>
        <sys_scope display_value="AMP2.0">a39c21588331f210d18398c6feaad3b6</sys_scope>
        <sys_update_name>sys_security_acl_4b7a1d8583317e10d18398c6feaad3c0</sys_update_name>
        <sys_updated_by>admin</sys_updated_by>
        <sys_updated_on>2025-12-12 02:00:17</sys_updated_on>
        <type display_value="record">record</type>
    </sys_security_acl>
<sys_update_version action="INSERT_OR_UPDATE">
        <action>DELETE</action>
        <application display_value="AMP2.0">a39c21588331f210d18398c6feaad3b6</application>
        <comments/>
        <file_path/>
        <instance_id>277b2d65dbf7cc1025011bbc32961966</instance_id>
        <instance_name>nsdeskdev</instance_name>
        <name>sys_security_acl_4b7a1d8583317e10d18398c6feaad3c0</name>
        <order/>
        <payload><![CDATA[<?xml version="1.0" encoding="UTF-8"?><record_update table="sys_security_acl">
    <sys_security_acl action="INSERT_OR_UPDATE">
        <active>true</active>
        <admin_overrides>true</admin_overrides>
        <advanced>false</advanced>
        <applies_to/>
        <condition/>
        <controlled_by_refs/>
        <decision_type>allow</decision_type>
        <description/>
        <local_or_existing>Existing</local_or_existing>
        <name>x_1831875_amp2_0_complex</name>
        <operation display_value="write">write</operation>
        <script/>
        <security_attribute/>
        <sys_class_name>sys_security_acl</sys_class_name>
        <sys_created_by>admin</sys_created_by>
        <sys_created_on>2025-12-12 02:00:17</sys_created_on>
        <sys_id>4b7a1d8583317e10d18398c6feaad3c0</sys_id>
        <sys_mod_count>0</sys_mod_count>
        <sys_name>x_1831875_amp2_0_complex</sys_name>
        <sys_package display_value="AMP2.0" source="x_1831875_amp2_0">a39c21588331f210d18398c6feaad3b6</sys_package>
        <sys_policy/>
        <sys_scope display_value="AMP2.0">a39c21588331f210d18398c6feaad3b6</sys_scope>
        <sys_update_name>sys_security_acl_4b7a1d8583317e10d18398c6feaad3c0</sys_update_name>
        <sys_updated_by>admin</sys_updated_by>
        <sys_updated_on>2025-12-12 02:00:17</sys_updated_on>
        <type display_value="record">record</type>
    </sys_security_acl>
</record_update>]]></payload>
        <payload_hash>1976299378</payload_hash>
        <record_name>x_1831875_amp2_0_complex</record_name>
        <reverted_from/>
        <source>c7138b26477132506ca043ff336d439d</source>
        <source_table>sys_upgrade_history</source_table>
        <state>previous</state>
        <sys_created_by>ryann.wiley</sys_created_by>
        <sys_created_on>2025-12-17 01:31:14</sys_created_on>
        <sys_id>d6c3c32e477132506ca043ff336d434d</sys_id>
        <sys_mod_count>0</sys_mod_count>
        <sys_recorded_at>19b29eecd0e0000001</sys_recorded_at>
        <sys_updated_by>ryann.wiley</sys_updated_by>
        <sys_updated_on>2025-12-17 01:31:14</sys_updated_on>
        <type>Access Control</type>
        <update_guid>96c3c32e8271325022b38ff5b968414d</update_guid>
        <update_guid_history>96c3c32e8271325022b38ff5b968414d:1976299378</update_guid_history>
    </sys_update_version>
    <sys_metadata_delete action="INSERT_OR_UPDATE">
        <sys_audit_delete/>
        <sys_class_name>sys_metadata_delete</sys_class_name>
        <sys_created_by>admin</sys_created_by>
        <sys_created_on>2026-01-12 14:54:03</sys_created_on>
        <sys_customer_update>false</sys_customer_update>
        <sys_db_object display_value="" name="sys_security_acl">sys_security_acl</sys_db_object>
        <sys_id>0650aeac88a54fb08594e82c094e6900</sys_id>
        <sys_metadata>4b7a1d8583317e10d18398c6feaad3c0</sys_metadata>
        <sys_mod_count>0</sys_mod_count>
        <sys_name>x_1831875_amp2_0_complex</sys_name>
        <sys_package display_value="AMP2.0" source="x_1831875_amp2_0">a39c21588331f210d18398c6feaad3b6</sys_package>
        <sys_parent display_value="">b823cf26477132506ca043ff336d43e0</sys_parent>
        <sys_policy/>
        <sys_replace_on_upgrade>false</sys_replace_on_upgrade>
        <sys_scope display_value="AMP2.0">a39c21588331f210d18398c6feaad3b6</sys_scope>
        <sys_scope_delete display_value="">08a977a4ad7d4f1cab12239157777c69</sys_scope_delete>
        <sys_update_name>sys_security_acl_4b7a1d8583317e10d18398c6feaad3c0</sys_update_name>
        <sys_update_version display_value="sys_security_acl_4b7a1d8583317e10d18398c6feaad3c0">d6c3c32e477132506ca043ff336d434d</sys_update_version>
        <sys_updated_by>admin</sys_updated_by>
        <sys_updated_on>2026-01-12 14:54:03</sys_updated_on>
    </sys_metadata_delete>
</record_update>
